aliyunsdkwaf_openapi/__init__.py
aliyunsdkwaf_openapi/endpoint.py
aliyunsdkwaf_openapi/request/__init__.py
aliyunsdkwaf_openapi/request/v20190910/CreateCertificateByCertificateIdRequest.py
aliyunsdkwaf_openapi/request/v20190910/CreateCertificateRequest.py
aliyunsdkwaf_openapi/request/v20190910/CreateDomainRequest.py
aliyunsdkwaf_openapi/request/v20190910/CreateProtectionModuleRuleRequest.py
aliyunsdkwaf_openapi/request/v20190910/DeleteDomainRequest.py
aliyunsdkwaf_openapi/request/v20190910/DeleteInstanceRequest.py
aliyunsdkwaf_openapi/request/v20190910/DeleteProtectionModuleRuleRequest.py
aliyunsdkwaf_openapi/request/v20190910/DescribeCertMatchStatusRequest.py
aliyunsdkwaf_openapi/request/v20190910/DescribeCertificatesRequest.py
aliyunsdkwaf_openapi/request/v20190910/DescribeDomainAdvanceConfigsRequest.py
aliyunsdkwaf_openapi/request/v20190910/DescribeDomainBasicConfigsRequest.py
aliyunsdkwaf_openapi/request/v20190910/DescribeDomainListRequest.py
aliyunsdkwaf_openapi/request/v20190910/DescribeDomainNamesRequest.py
aliyunsdkwaf_openapi/request/v20190910/DescribeDomainRequest.py
aliyunsdkwaf_openapi/request/v20190910/DescribeDomainRuleGroupRequest.py
aliyunsdkwaf_openapi/request/v20190910/DescribeInstanceInfoRequest.py
aliyunsdkwaf_openapi/request/v20190910/DescribeInstanceSpecInfoRequest.py
aliyunsdkwaf_openapi/request/v20190910/DescribeLogServiceStatusRequest.py
aliyunsdkwaf_openapi/request/v20190910/DescribeProtectionModuleCodeConfigRequest.py
aliyunsdkwaf_openapi/request/v20190910/DescribeProtectionModuleModeRequest.py
aliyunsdkwaf_openapi/request/v20190910/DescribeProtectionModuleRulesRequest.py
aliyunsdkwaf_openapi/request/v20190910/DescribeProtectionModuleStatusRequest.py
aliyunsdkwaf_openapi/request/v20190910/DescribeRuleGroupsRequest.py
aliyunsdkwaf_openapi/request/v20190910/DescribeRulesRequest.py
aliyunsdkwaf_openapi/request/v20190910/DescribeWafSourceIpSegmentRequest.py
aliyunsdkwaf_openapi/request/v20190910/ModifyDomainIpv6StatusRequest.py
aliyun_python_sdk_waf_openapi-1.1.10.dist-info/LICENSE
aliyun_python_sdk_waf_openapi-1.1.10.dist-info/METADATA
aliyun_python_sdk_waf_openapi-1.1.10.dist-info/WHEEL
aliyun_python_sdk_waf_openapi-1.1.10.dist-info/top_level.txt
aliyun_python_sdk_waf_openapi-1.1.10.dist-info/RECORD
